{"nodes": [{"id": "d_workplace_travelbuddy_travelbuddyapp_components_interactivemap_tsx", "label": "InteractiveMap.tsx", "file_type": "code", "source_file": "D:\\WorkPlace\\TravelBuddy\\travelbuddyapp\\components\\InteractiveMap.tsx", "source_location": "L1"}, {"id": "components_interactivemap_getcurrentlocation", "label": "getCurrentLocation()", "file_type": "code", "source_file": "D:\\WorkPlace\\TravelBuddy\\travelbuddyapp\\components\\InteractiveMap.tsx", "source_location": "L108"}, {"id": "components_interactivemap_handlemappress", "label": "handleMapPress()", "file_type": "code", "source_file": "D:\\WorkPlace\\TravelBuddy\\travelbuddyapp\\components\\InteractiveMap.tsx", "source_location": "L138"}, {"id": "components_interactivemap_searchlocation", "label": "searchLocation()", "file_type": "code", "source_file": "D:\\WorkPlace\\TravelBuddy\\travelbuddyapp\\components\\InteractiveMap.tsx", "source_location": "L173"}, {"id": "components_interactivemap_handlesearchtextchange", "label": "handleSearchTextChange()", "file_type": "code", "source_file": "D:\\WorkPlace\\TravelBuddy\\travelbuddyapp\\components\\InteractiveMap.tsx", "source_location": "L210"}, {"id": "components_interactivemap_selectsuggestion", "label": "selectSuggestion()", "file_type": "code", "source_file": "D:\\WorkPlace\\TravelBuddy\\travelbuddyapp\\components\\InteractiveMap.tsx", "source_location": "L226"}, {"id": "components_interactivemap_usecurrentlocationforpickup", "label": "useCurrentLocationForPickup()", "file_type": "code", "source_file": "D:\\WorkPlace\\TravelBuddy\\travelbuddyapp\\components\\InteractiveMap.tsx", "source_location": "L255"}, {"id": "components_interactivemap_swaplocations", "label": "swapLocations()", "file_type": "code", "source_file": "D:\\WorkPlace\\TravelBuddy\\travelbuddyapp\\components\\InteractiveMap.tsx", "source_location": "L300"}, {"id": "components_interactivemap_clearlocation", "label": "clearLocation()", "file_type": "code", "source_file": "D:\\WorkPlace\\TravelBuddy\\travelbuddyapp\\components\\InteractiveMap.tsx", "source_location": "L310"}, {"id": "components_interactivemap_fittocoordinates", "label": "fitToCoordinates()", "file_type": "code", "source_file": "D:\\WorkPlace\\TravelBuddy\\travelbuddyapp\\components\\InteractiveMap.tsx", "source_location": "L321"}, {"id": "components_interactivemap_handleconfirm", "label": "handleConfirm()", "file_type": "code", "source_file": "D:\\WorkPlace\\TravelBuddy\\travelbuddyapp\\components\\InteractiveMap.tsx", "source_location": "L336"}], "edges": [{"source": "d_workplace_travelbuddy_travelbuddyapp_components_interactivemap_tsx", "target": "react", "relation": "imports_from", "confidence": "EXTRACTED", "source_file": "D:\\WorkPlace\\TravelBuddy\\travelbuddyapp\\components\\InteractiveMap.tsx", "source_location": "L1", "weight": 1.0}, {"source": "d_workplace_travelbuddy_travelbuddyapp_components_interactivemap_tsx", "target": "react_native", "relation": "imports_from", "confidence": "EXTRACTED", "source_file": "D:\\WorkPlace\\TravelBuddy\\travelbuddyapp\\components\\InteractiveMap.tsx", "source_location": "L2", "weight": 1.0}, {"source": "d_workplace_travelbuddy_travelbuddyapp_components_interactivemap_tsx", "target": "react_native_maps", "relation": "imports_from", "confidence": "EXTRACTED", "source_file": "D:\\WorkPlace\\TravelBuddy\\travelbuddyapp\\components\\InteractiveMap.tsx", "source_location": "L14", "weight": 1.0}, {"source": "d_workplace_travelbuddy_travelbuddyapp_components_interactivemap_tsx", "target": "react_native_maps_directions", "relation": "imports_from", "confidence": "EXTRACTED", "source_file": "D:\\WorkPlace\\TravelBuddy\\travelbuddyapp\\components\\InteractiveMap.tsx", "source_location": "L15", "weight": 1.0}, {"source": "d_workplace_travelbuddy_travelbuddyapp_components_interactivemap_tsx", "target": "expo_location", "relation": "imports_from", "confidence": "EXTRACTED", "source_file": "D:\\WorkPlace\\TravelBuddy\\travelbuddyapp\\components\\InteractiveMap.tsx", "source_location": "L16", "weight": 1.0}, {"source": "d_workplace_travelbuddy_travelbuddyapp_components_interactivemap_tsx", "target": "d_workplace_travelbuddy_travelbuddyapp_contexts_themecontext", "relation": "imports_from", "confidence": "EXTRACTED", "source_file": "D:\\WorkPlace\\TravelBuddy\\travelbuddyapp\\components\\InteractiveMap.tsx", "source_location": "L17", "weight": 1.0}, {"source": "d_workplace_travelbuddy_travelbuddyapp_components_interactivemap_tsx", "target": "lucide_react_native", "relation": "imports_from", "confidence": "EXTRACTED", "source_file": "D:\\WorkPlace\\TravelBuddy\\travelbuddyapp\\components\\InteractiveMap.tsx", "source_location": "L18", "weight": 1.0}, {"source": "d_workplace_travelbuddy_travelbuddyapp_components_interactivemap_tsx", "target": "d_workplace_travelbuddy_travelbuddyapp_utils_permissions", "relation": "imports_from", "confidence": "EXTRACTED", "source_file": "D:\\WorkPlace\\TravelBuddy\\travelbuddyapp\\components\\InteractiveMap.tsx", "source_location": "L28", "weight": 1.0}, {"source": "d_workplace_travelbuddy_travelbuddyapp_components_interactivemap_tsx", "target": "components_interactivemap_getcurrentlocation", "relation": "contains", "confidence": "EXTRACTED", "source_file": "D:\\WorkPlace\\TravelBuddy\\travelbuddyapp\\components\\InteractiveMap.tsx", "source_location": "L108", "weight": 1.0}, {"source": "d_workplace_travelbuddy_travelbuddyapp_components_interactivemap_tsx", "target": "components_interactivemap_handlemappress", "relation": "contains", "confidence": "EXTRACTED", "source_file": "D:\\WorkPlace\\TravelBuddy\\travelbuddyapp\\components\\InteractiveMap.tsx", "source_location": "L138", "weight": 1.0}, {"source": "d_workplace_travelbuddy_travelbuddyapp_components_interactivemap_tsx", "target": "components_interactivemap_searchlocation", "relation": "contains", "confidence": "EXTRACTED", "source_file": "D:\\WorkPlace\\TravelBuddy\\travelbuddyapp\\components\\InteractiveMap.tsx", "source_location": "L173", "weight": 1.0}, {"source": "d_workplace_travelbuddy_travelbuddyapp_components_interactivemap_tsx", "target": "components_interactivemap_handlesearchtextchange", "relation": "contains", "confidence": "EXTRACTED", "source_file": "D:\\WorkPlace\\TravelBuddy\\travelbuddyapp\\components\\InteractiveMap.tsx", "source_location": "L210", "weight": 1.0}, {"source": "d_workplace_travelbuddy_travelbuddyapp_components_interactivemap_tsx", "target": "components_interactivemap_selectsuggestion", "relation": "contains", "confidence": "EXTRACTED", "source_file": "D:\\WorkPlace\\TravelBuddy\\travelbuddyapp\\components\\InteractiveMap.tsx", "source_location": "L226", "weight": 1.0}, {"source": "d_workplace_travelbuddy_travelbuddyapp_components_interactivemap_tsx", "target": "components_interactivemap_usecurrentlocationforpickup", "relation": "contains", "confidence": "EXTRACTED", "source_file": "D:\\WorkPlace\\TravelBuddy\\travelbuddyapp\\components\\InteractiveMap.tsx", "source_location": "L255", "weight": 1.0}, {"source": "d_workplace_travelbuddy_travelbuddyapp_components_interactivemap_tsx", "target": "components_interactivemap_swaplocations", "relation": "contains", "confidence": "EXTRACTED", "source_file": "D:\\WorkPlace\\TravelBuddy\\travelbuddyapp\\components\\InteractiveMap.tsx", "source_location": "L300", "weight": 1.0}, {"source": "d_workplace_travelbuddy_travelbuddyapp_components_interactivemap_tsx", "target": "components_interactivemap_clearlocation", "relation": "contains", "confidence": "EXTRACTED", "source_file": "D:\\WorkPlace\\TravelBuddy\\travelbuddyapp\\components\\InteractiveMap.tsx", "source_location": "L310", "weight": 1.0}, {"source": "d_workplace_travelbuddy_travelbuddyapp_components_interactivemap_tsx", "target": "components_interactivemap_fittocoordinates", "relation": "contains", "confidence": "EXTRACTED", "source_file": "D:\\WorkPlace\\TravelBuddy\\travelbuddyapp\\components\\InteractiveMap.tsx", "source_location": "L321", "weight": 1.0}, {"source": "d_workplace_travelbuddy_travelbuddyapp_components_interactivemap_tsx", "target": "components_interactivemap_handleconfirm", "relation": "contains", "confidence": "EXTRACTED", "source_file": "D:\\WorkPlace\\TravelBuddy\\travelbuddyapp\\components\\InteractiveMap.tsx", "source_location": "L336", "weight": 1.0}], "raw_calls": [{"caller_nid": "components_interactivemap_getcurrentlocation", "callee": "setIsLoadingLocation", "source_file": "D:\\WorkPlace\\TravelBuddy\\travelbuddyapp\\components\\InteractiveMap.tsx", "source_location": "L109"}, {"caller_nid": "components_interactivemap_getcurrentlocation", "callee": "requestLocationPermission", "source_file": "D:\\WorkPlace\\TravelBuddy\\travelbuddyapp\\components\\InteractiveMap.tsx", "source_location": "L111"}, {"caller_nid": "components_interactivemap_getcurrentlocation", "callee": "alert", "source_file": "D:\\WorkPlace\\TravelBuddy\\travelbuddyapp\\components\\InteractiveMap.tsx", "source_location": "L113"}, {"caller_nid": "components_interactivemap_getcurrentlocation", "callee": "getCurrentPositionAsync", "source_file": "D:\\WorkPlace\\TravelBuddy\\travelbuddyapp\\components\\InteractiveMap.tsx", "source_location": "L117"}, {"caller_nid": "components_interactivemap_getcurrentlocation", "callee": "setRegion", "source_file": "D:\\WorkPlace\\TravelBuddy\\travelbuddyapp\\components\\InteractiveMap.tsx", "source_location": "L128"}, {"caller_nid": "components_interactivemap_getcurrentlocation", "callee": "animateToRegion", "source_file": "D:\\WorkPlace\\TravelBuddy\\travelbuddyapp\\components\\InteractiveMap.tsx", "source_location": "L129"}, {"caller_nid": "components_interactivemap_getcurrentlocation", "callee": "error", "source_file": "D:\\WorkPlace\\TravelBuddy\\travelbuddyapp\\components\\InteractiveMap.tsx", "source_location": "L131"}, {"caller_nid": "components_interactivemap_getcurrentlocation", "callee": "alert", "source_file": "D:\\WorkPlace\\TravelBuddy\\travelbuddyapp\\components\\InteractiveMap.tsx", "source_location": "L132"}, {"caller_nid": "components_interactivemap_getcurrentlocation", "callee": "setIsLoadingLocation", "source_file": "D:\\WorkPlace\\TravelBuddy\\travelbuddyapp\\components\\InteractiveMap.tsx", "source_location": "L134"}, {"caller_nid": "components_interactivemap_handlemappress", "callee": "reverseGeocodeAsync", "source_file": "D:\\WorkPlace\\TravelBuddy\\travelbuddyapp\\components\\InteractiveMap.tsx", "source_location": "L142"}, {"caller_nid": "components_interactivemap_handlemappress", "callee": "trim", "source_file": "D:\\WorkPlace\\TravelBuddy\\travelbuddyapp\\components\\InteractiveMap.tsx", "source_location": "L149"}, {"caller_nid": "components_interactivemap_handlemappress", "callee": "setFromLocation", "source_file": "D:\\WorkPlace\\TravelBuddy\\travelbuddyapp\\components\\InteractiveMap.tsx", "source_location": "L158"}, {"caller_nid": "components_interactivemap_handlemappress", "callee": "setFromSearchText", "source_file": "D:\\WorkPlace\\TravelBuddy\\travelbuddyapp\\components\\InteractiveMap.tsx", "source_location": "L159"}, {"caller_nid": "components_interactivemap_handlemappress", "callee": "setActiveField", "source_file": "D:\\WorkPlace\\TravelBuddy\\travelbuddyapp\\components\\InteractiveMap.tsx", "source_location": "L160"}, {"caller_nid": "components_interactivemap_handlemappress", "callee": "setToLocation", "source_file": "D:\\WorkPlace\\TravelBuddy\\travelbuddyapp\\components\\InteractiveMap.tsx", "source_location": "L162"}, {"caller_nid": "components_interactivemap_handlemappress", "callee": "setToSearchText", "source_file": "D:\\WorkPlace\\TravelBuddy\\travelbuddyapp\\components\\InteractiveMap.tsx", "source_location": "L163"}, {"caller_nid": "components_interactivemap_handlemappress", "callee": "setActiveField", "source_file": "D:\\WorkPlace\\TravelBuddy\\travelbuddyapp\\components\\InteractiveMap.tsx", "source_location": "L164"}, {"caller_nid": "components_interactivemap_handlemappress", "callee": "error", "source_file": "D:\\WorkPlace\\TravelBuddy\\travelbuddyapp\\components\\InteractiveMap.tsx", "source_location": "L168"}, {"caller_nid": "components_interactivemap_handlemappress", "callee": "alert", "source_file": "D:\\WorkPlace\\TravelBuddy\\travelbuddyapp\\components\\InteractiveMap.tsx", "source_location": "L169"}, {"caller_nid": "components_interactivemap_searchlocation", "callee": "setSearchSuggestions", "source_file": "D:\\WorkPlace\\TravelBuddy\\travelbuddyapp\\components\\InteractiveMap.tsx", "source_location": "L175"}, {"caller_nid": "components_interactivemap_searchlocation", "callee": "setIsSearching", "source_file": "D:\\WorkPlace\\TravelBuddy\\travelbuddyapp\\components\\InteractiveMap.tsx", "source_location": "L179"}, {"caller_nid": "components_interactivemap_searchlocation", "callee": "fetch", "source_file": "D:\\WorkPlace\\TravelBuddy\\travelbuddyapp\\components\\InteractiveMap.tsx", "source_location": "L181"}, {"caller_nid": "components_interactivemap_searchlocation", "callee": "encodeURIComponent", "source_file": "D:\\WorkPlace\\TravelBuddy\\travelbuddyapp\\components\\InteractiveMap.tsx", "source_location": "L182"}, {"caller_nid": "components_interactivemap_searchlocation", "callee": "json", "source_file": "D:\\WorkPlace\\TravelBuddy\\travelbuddyapp\\components\\InteractiveMap.tsx", "source_location": "L189"}, {"caller_nid": "components_interactivemap_searchlocation", "callee": "map", "source_file": "D:\\WorkPlace\\TravelBuddy\\travelbuddyapp\\components\\InteractiveMap.tsx", "source_location": "L191"}, {"caller_nid": "components_interactivemap_searchlocation", "callee": "setSearchSuggestions", "source_file": "D:\\WorkPlace\\TravelBuddy\\travelbuddyapp\\components\\InteractiveMap.tsx", "source_location": "L202"}, {"caller_nid": "components_interactivemap_searchlocation", "callee": "error", "source_file": "D:\\WorkPlace\\TravelBuddy\\travelbuddyapp\\components\\InteractiveMap.tsx", "source_location": "L204"}, {"caller_nid": "components_interactivemap_searchlocation", "callee": "setIsSearching", "source_file": "D:\\WorkPlace\\TravelBuddy\\travelbuddyapp\\components\\InteractiveMap.tsx", "source_location": "L206"}, {"caller_nid": "components_interactivemap_handlesearchtextchange", "callee": "setFromSearchText", "source_file": "D:\\WorkPlace\\TravelBuddy\\travelbuddyapp\\components\\InteractiveMap.tsx", "source_location": "L212"}, {"caller_nid": "components_interactivemap_handlesearchtextchange", "callee": "setToSearchText", "source_file": "D:\\WorkPlace\\TravelBuddy\\travelbuddyapp\\components\\InteractiveMap.tsx", "source_location": "L214"}, {"caller_nid": "components_interactivemap_handlesearchtextchange", "callee": "clearTimeout", "source_file": "D:\\WorkPlace\\TravelBuddy\\travelbuddyapp\\components\\InteractiveMap.tsx", "source_location": "L218"}, {"caller_nid": "components_interactivemap_handlesearchtextchange", "callee": "setTimeout", "source_file": "D:\\WorkPlace\\TravelBuddy\\travelbuddyapp\\components\\InteractiveMap.tsx", "source_location": "L221"}, {"caller_nid": "components_interactivemap_selectsuggestion", "callee": "setFromLocation", "source_file": "D:\\WorkPlace\\TravelBuddy\\travelbuddyapp\\components\\InteractiveMap.tsx", "source_location": "L235"}, {"caller_nid": "components_interactivemap_selectsuggestion", "callee": "setFromSearchText", "source_file": "D:\\WorkPlace\\TravelBuddy\\travelbuddyapp\\components\\InteractiveMap.tsx", "source_location": "L236"}, {"caller_nid": "components_interactivemap_selectsuggestion", "callee": "setToLocation", "source_file": "D:\\WorkPlace\\TravelBuddy\\travelbuddyapp\\components\\InteractiveMap.tsx", "source_location": "L238"}, {"caller_nid": "components_interactivemap_selectsuggestion", "callee": "setToSearchText", "source_file": "D:\\WorkPlace\\TravelBuddy\\travelbuddyapp\\components\\InteractiveMap.tsx", "source_location": "L239"}, {"caller_nid": "components_interactivemap_selectsuggestion", "callee": "setSearchSuggestions", "source_file": "D:\\WorkPlace\\TravelBuddy\\travelbuddyapp\\components\\InteractiveMap.tsx", "source_location": "L242"}, {"caller_nid": "components_interactivemap_selectsuggestion", "callee": "setActiveField", "source_file": "D:\\WorkPlace\\TravelBuddy\\travelbuddyapp\\components\\InteractiveMap.tsx", "source_location": "L243"}, {"caller_nid": "components_interactivemap_selectsuggestion", "callee": "animateToRegion", "source_file": "D:\\WorkPlace\\TravelBuddy\\travelbuddyapp\\components\\InteractiveMap.tsx", "source_location": "L252"}, {"caller_nid": "components_interactivemap_usecurrentlocationforpickup", "callee": "setIsLoadingLocation", "source_file": "D:\\WorkPlace\\TravelBuddy\\travelbuddyapp\\components\\InteractiveMap.tsx", "source_location": "L256"}, {"caller_nid": "components_interactivemap_usecurrentlocationforpickup", "callee": "requestLocationPermission", "source_file": "D:\\WorkPlace\\TravelBuddy\\travelbuddyapp\\components\\InteractiveMap.tsx", "source_location": "L258"}, {"caller_nid": "components_interactivemap_usecurrentlocationforpickup", "callee": "getCurrentPositionAsync", "source_file": "D:\\WorkPlace\\TravelBuddy\\travelbuddyapp\\components\\InteractiveMap.tsx", "source_location": "L261"}, {"caller_nid": "components_interactivemap_usecurrentlocationforpickup", "callee": "reverseGeocodeAsync", "source_file": "D:\\WorkPlace\\TravelBuddy\\travelbuddyapp\\components\\InteractiveMap.tsx", "source_location": "L265"}, {"caller_nid": "components_interactivemap_usecurrentlocationforpickup", "callee": "trim", "source_file": "D:\\WorkPlace\\TravelBuddy\\travelbuddyapp\\components\\InteractiveMap.tsx", "source_location": "L272"}, {"caller_nid": "components_interactivemap_usecurrentlocationforpickup", "callee": "setFromLocation", "source_file": "D:\\WorkPlace\\TravelBuddy\\travelbuddyapp\\components\\InteractiveMap.tsx", "source_location": "L280"}, {"caller_nid": "components_interactivemap_usecurrentlocationforpickup", "callee": "setFromSearchText", "source_file": "D:\\WorkPlace\\TravelBuddy\\travelbuddyapp\\components\\InteractiveMap.tsx", "source_location": "L281"}, {"caller_nid": "components_interactivemap_usecurrentlocationforpickup", "callee": "setActiveField", "source_file": "D:\\WorkPlace\\TravelBuddy\\travelbuddyapp\\components\\InteractiveMap.tsx", "source_location": "L282"}, {"caller_nid": "components_interactivemap_usecurrentlocationforpickup", "callee": "animateToRegion", "source_file": "D:\\WorkPlace\\TravelBuddy\\travelbuddyapp\\components\\InteractiveMap.tsx", "source_location": "L290"}, {"caller_nid": "components_interactivemap_usecurrentlocationforpickup", "callee": "error", "source_file": "D:\\WorkPlace\\TravelBuddy\\travelbuddyapp\\components\\InteractiveMap.tsx", "source_location": "L293"}, {"caller_nid": "components_interactivemap_usecurrentlocationforpickup", "callee": "alert", "source_file": "D:\\WorkPlace\\TravelBuddy\\travelbuddyapp\\components\\InteractiveMap.tsx", "source_location": "L294"}, {"caller_nid": "components_interactivemap_usecurrentlocationforpickup", "callee": "setIsLoadingLocation", "source_file": "D:\\WorkPlace\\TravelBuddy\\travelbuddyapp\\components\\InteractiveMap.tsx", "source_location": "L296"}, {"caller_nid": "components_interactivemap_swaplocations", "callee": "setFromLocation", "source_file": "D:\\WorkPlace\\TravelBuddy\\travelbuddyapp\\components\\InteractiveMap.tsx", "source_location": "L304"}, {"caller_nid": "components_interactivemap_swaplocations", "callee": "setFromSearchText", "source_file": "D:\\WorkPlace\\TravelBuddy\\travelbuddyapp\\components\\InteractiveMap.tsx", "source_location": "L305"}, {"caller_nid": "components_interactivemap_swaplocations", "callee": "setToLocation", "source_file": "D:\\WorkPlace\\TravelBuddy\\travelbuddyapp\\components\\InteractiveMap.tsx", "source_location": "L306"}, {"caller_nid": "components_interactivemap_swaplocations", "callee": "setToSearchText", "source_file": "D:\\WorkPlace\\TravelBuddy\\travelbuddyapp\\components\\InteractiveMap.tsx", "source_location": "L307"}, {"caller_nid": "components_interactivemap_clearlocation", "callee": "setFromLocation", "source_file": "D:\\WorkPlace\\TravelBuddy\\travelbuddyapp\\components\\InteractiveMap.tsx", "source_location": "L312"}, {"caller_nid": "components_interactivemap_clearlocation", "callee": "setFromSearchText", "source_file": "D:\\WorkPlace\\TravelBuddy\\travelbuddyapp\\components\\InteractiveMap.tsx", "source_location": "L313"}, {"caller_nid": "components_interactivemap_clearlocation", "callee": "setToLocation", "source_file": "D:\\WorkPlace\\TravelBuddy\\travelbuddyapp\\components\\InteractiveMap.tsx", "source_location": "L315"}, {"caller_nid": "components_interactivemap_clearlocation", "callee": "setToSearchText", "source_file": "D:\\WorkPlace\\TravelBuddy\\travelbuddyapp\\components\\InteractiveMap.tsx", "source_location": "L316"}, {"caller_nid": "components_interactivemap_clearlocation", "callee": "setShowDirections", "source_file": "D:\\WorkPlace\\TravelBuddy\\travelbuddyapp\\components\\InteractiveMap.tsx", "source_location": "L318"}, {"caller_nid": "components_interactivemap_handleconfirm", "callee": "onLocationsSelected", "source_file": "D:\\WorkPlace\\TravelBuddy\\travelbuddyapp\\components\\InteractiveMap.tsx", "source_location": "L338"}, {"caller_nid": "components_interactivemap_handleconfirm", "callee": "alert", "source_file": "D:\\WorkPlace\\TravelBuddy\\travelbuddyapp\\components\\InteractiveMap.tsx", "source_location": "L340"}]}